gradable/__init__.py
gradable/foo.py
gradable-0.0.1a0.dist-info/LICENSE
gradable-0.0.1a0.dist-info/METADATA
gradable-0.0.1a0.dist-info/WHEEL
gradable-0.0.1a0.dist-info/RECORD
