Metadata-Version: 2.1
Name: gradable
Version: 0.0.1a0
Summary: Gradable reward signals
Home-page: https://github.com/nlile/gradable
Author: nlile
Author-email: nathan@synthlabs.ao
Requires-Python: >=3.8,<4.0
Classifier: Programming Language :: Python :: 3
Classifier: Programming Language :: Python :: 3.8
Classifier: Programming Language :: Python :: 3.9
Classifier: Programming Language :: Python :: 3.10
Classifier: Programming Language :: Python :: 3.11
Classifier: Programming Language :: Python :: 3.12
Project-URL: Documentation, https://nlile.github.io/gradable/
Project-URL: Repository, https://github.com/nlile/gradable
